chatgpt_uoapi/__init__.py
chatgpt_uoapi/app.py
chatgpt_uoapi/backend.py
chatgpt_uoapi/browser.py
chatgpt_uoapi/utils.py
chatgpt_uoapi-1.1.4.dist-info/LICENSE
chatgpt_uoapi-1.1.4.dist-info/METADATA
chatgpt_uoapi-1.1.4.dist-info/WHEEL
chatgpt_uoapi-1.1.4.dist-info/top_level.txt
chatgpt_uoapi-1.1.4.dist-info/RECORD
