Metadata-Version: 2.1
Name: chatgpt-uoapi
Version: 1.1.4
Summary: Short description of your package.
Author-email: Shaukat Ali Khan <youngdevelopersk@email.com>
License: MIT License
Classifier: Programming Language :: Python :: 3
Classifier: License :: OSI Approved :: MIT License
Classifier: Operating System :: OS Independent
Requires-Python: >=3.12
License-File: LICENSE
Requires-Dist: selenium>=4.29.0
Requires-Dist: undetected-chromedriver>=3.5.5
Requires-Dist: webdriver-manager>=4.0.2
Requires-Dist: pyperclip>=1.9.0
Requires-Dist: setuptools>=75.8.2
Requires-Dist: pyyaml>=6.0.2
